hubstorage/__init__.py
hubstorage/activity.py
hubstorage/batchuploader.py
hubstorage/client.py
hubstorage/collectionsrt.py
hubstorage/frontier.py
hubstorage/job.py
hubstorage/jobq.py
hubstorage/project.py
hubstorage/resourcetype.py
hubstorage/serialization.py
hubstorage/utils.py
hubstorage/VERSION
tests/__init__.py
tests/hstestcase.py
tests/test_activity.py
tests/test_batchuploader.py
tests/test_client.py
tests/test_collections.py
tests/test_frontier.py
tests/test_jobq.py
tests/test_jobsmeta.py
tests/test_project.py
tests/test_retry.py
tests/test_system.py
tests/testutil.py
hubstorage-0.23.6.dist-info/top_level.txt
hubstorage-0.23.6.dist-info/METADATA
hubstorage-0.23.6.dist-info/DESCRIPTION.rst
hubstorage-0.23.6.dist-info/metadata.json
hubstorage-0.23.6.dist-info/WHEEL
hubstorage-0.23.6.dist-info/RECORD
